python_enigma/__init__.py
python_enigma/__main__.py
python_enigma/catalogue.json
python_enigma/csvtojson.py
python_enigma/enigma.py
python_enigma/helloworld.py
python_enigma/table_rotors.csv
python_enigma-1.1.4.dist-info/METADATA
python_enigma-1.1.4.dist-info/WHEEL
python_enigma-1.1.4.dist-info/licenses/LICENSE
python_enigma-1.1.4.dist-info/RECORD
