Metadata-Version: 2.4
Name: python_enigma
Version: 1.1.4
Summary: A simple module which adds Enigma Machine-emulating functionality to your python projects.
Project-URL: Homepage, https://github.com/ZAdamMac/python-enigma/
Project-URL: Changelog, https://github.com/ZAdamMac/python-enigma/blob/master/CHANGELOG.md
Project-URL: Repository, https://github.com/ZAdamMac/python-enigma.git
Author: Zachary Adam-MacEwen
Maintainer-email: Jeffrey P Goldberg <jeffrey@goldmark.org>
License-File: LICENSE
Classifier: Development Status :: 4 - Beta
Classifier: Intended Audience :: Developers
Classifier: Intended Audience :: Education
Classifier: License :: OSI Approved :: Apache Software License
Classifier: Programming Language :: Python :: 3
Requires-Python: >=3.6
